sona/__init__.py
sona/__main__.py
sona/core/commands.py
sona/core/exceptions.py
sona/core/inferencer.py
sona/core/messages/__init__.py
sona/core/messages/base.py
sona/core/messages/context.py
sona/core/messages/file.py
sona/core/messages/job.py
sona/core/messages/result.py
sona/core/messages/state.py
sona/core/middlewares/__init__.py
sona/core/middlewares/base.py
sona/core/middlewares/supervisors.py
sona/core/storages/__init__.py
sona/core/storages/azure.py
sona/core/storages/base.py
sona/core/storages/filters/audio.py
sona/core/storages/gcs.py
sona/core/storages/local.py
sona/core/storages/s3.py
sona/core/storages/sources/__init__.py
sona/core/storages/sources/azure.py
sona/core/storages/sources/base.py
sona/core/storages/sources/gcs.py
sona/core/storages/sources/http.py
sona/core/storages/sources/local.py
sona/core/storages/sources/s3.py
sona/core/storages/sources/youtube.py
sona/core/stream/inferencer.py
sona/core/stream/messages/__init__.py
sona/core/stream/messages/context.py
sona/core/stream/messages/streamdata.py
sona/core/stream/parsers/audio.py
sona/settings.py
sona/sidecar/commands.py
sona/sidecar/sidecars.py
sona/utils.py
sona/web/commands.py
sona/web/http/routes.py
sona/web/messages/__init__.py
sona/web/messages/requests.py
sona/web/messages/responses.py
sona/web/server.py
sona/web/webrtc/handlers.py
sona/web/webrtc/routes.py
sona/web/webrtc/sessions.py
sona/web/webrtc/static/client.js
sona/web/webrtc/static/webrtc.html
sona/web/webrtc/tracks.py
sona/worker/__init__.py
sona/worker/commands.py
sona/worker/consumers/__init__.py
sona/worker/consumers/azure.py
sona/worker/consumers/base.py
sona/worker/consumers/kafka.py
sona/worker/consumers/redis.py
sona/worker/consumers/sqs.py
sona/worker/producers/__init__.py
sona/worker/producers/azure.py
sona/worker/producers/base.py
sona/worker/producers/kafka.py
sona/worker/producers/redis.py
sona/worker/producers/sqs.py
sona/worker/workers.py
dwave_sona_core-1.6.7.dist-info/METADATA
dwave_sona_core-1.6.7.dist-info/WHEEL
dwave_sona_core-1.6.7.dist-info/licenses/LICENSE
dwave_sona_core-1.6.7.dist-info/RECORD
