Metadata-Version: 2.4
Name: dwave-sona-core
Version: 1.6.7
Summary: 
License-File: LICENSE
Author: dwave-dev
Requires-Python: >=3.9,<4.0
Classifier: Programming Language :: Python :: 3
Classifier: Programming Language :: Python :: 3.9
Classifier: Programming Language :: Python :: 3.10
Classifier: Programming Language :: Python :: 3.11
Classifier: Programming Language :: Python :: 3.12
Classifier: Programming Language :: Python :: 3.13
Classifier: Programming Language :: Python :: 3.14
Requires-Dist: aiofile (>=3.8.8,<4.0.0)
Requires-Dist: aiohttp (>=3.9.5,<4.0.0)
Requires-Dist: aiortc (>=1.5.0,<2.0.0)
Requires-Dist: azure-identity (>=1.17.1,<2.0.0)
Requires-Dist: azure-storage-blob (>=12.20.0,<13.0.0)
Requires-Dist: azure-storage-queue (>=12.10.0,<13.0.0)
Requires-Dist: boto3 (>=1.34.138,<2.0.0)
Requires-Dist: fastapi (>=0.111.0,<0.112.0)
Requires-Dist: filelock (>=3.15.4,<4.0.0)
Requires-Dist: google-cloud-storage (>=3.1.0,<4.0.0)
Requires-Dist: hypercorn (>=0.17.3,<0.18.0)
Requires-Dist: loguru (>=0.7.2,<0.8.0)
Requires-Dist: pydantic-settings (>=2.3.4,<3.0.0)
Requires-Dist: requests (>=2.32.5,<3.0.0)
Requires-Dist: yt-dlp
